Metadata-Version: 2.4
Name: medllm-finetune-rag
Version: 0.1.2
Summary: A comprehensive toolkit for fine-tuning medical large language models with RAG capabilities
Home-page: https://github.com/chenxingqiang/medllm-finetune-rag
Author: Xingqiang Chen
Author-email: Xingqiang Chen <joy66777@gmail.com>
Maintainer-email: Xingqiang Chen <joy66777@gmail.com>
License-Expression: MIT
Project-URL: Homepage, https://github.com/chenxingqiang/medllm-finetune-rag
Project-URL: Repository, https://github.com/chenxingqiang/medllm-finetune-rag
Project-URL: Documentation, https://github.com/chenxingqiang/medllm-finetune-rag/blob/main/README.md
Project-URL: Bug Reports, https://github.com/chenxingqiang/medllm-finetune-rag/issues
Keywords: medical,llm,fine-tuning,rag,qwen,healthcare,nlp,ai
Classifier: Development Status :: 4 - Beta
Classifier: Intended Audience :: Developers
Classifier: Intended Audience :: Healthcare Industry
Classifier: Intended Audience :: Science/Research
Classifier: Operating System :: OS Independent
Classifier: Programming Language :: Python :: 3
Classifier: Programming Language :: Python :: 3.8
Classifier: Programming Language :: Python :: 3.9
Classifier: Programming Language :: Python :: 3.10
Classifier: Programming Language :: Python :: 3.11
Classifier: Programming Language :: Python :: 3.12
Classifier: Topic :: Scientific/Engineering :: Artificial Intelligence
Classifier: Topic :: Scientific/Engineering :: Medical Science Apps.
Classifier: Topic :: Software Development :: Libraries :: Python Modules
Requires-Python: >=3.8
License-File: LICENSE
Requires-Dist: torch>=2.0.0
Requires-Dist: transformers>=4.35.0
Requires-Dist: tokenizers>=0.14.0
Requires-Dist: datasets>=2.14.0
Requires-Dist: accelerate>=0.24.0
Requires-Dist: peft>=0.6.0
Requires-Dist: trl>=0.7.0
Requires-Dist: scikit-learn>=1.3.0
Requires-Dist: numpy>=1.24.0
Requires-Dist: pandas>=2.0.0
Requires-Dist: sentence-transformers>=2.2.0
Requires-Dist: raganything[all]
Requires-Dist: lightrag
Requires-Dist: chromadb>=0.4.0
Requires-Dist: tqdm>=4.65.0
Requires-Dist: python-dotenv>=1.0.0
Requires-Dist: huggingface-hub>=0.20.0
Requires-Dist: PyYAML>=6.0
Provides-Extra: unsloth
Requires-Dist: unsloth_zoo; extra == "unsloth"
Provides-Extra: rag
Provides-Extra: gpu
Requires-Dist: bitsandbytes>=0.41.0; extra == "gpu"
Provides-Extra: dev
Requires-Dist: black>=23.0.0; extra == "dev"
Requires-Dist: flake8>=6.0.0; extra == "dev"
Requires-Dist: pytest>=7.0.0; extra == "dev"
Requires-Dist: jupyter>=1.0.0; extra == "dev"
Provides-Extra: viz
Requires-Dist: matplotlib>=3.7.0; extra == "viz"
Requires-Dist: seaborn>=0.12.0; extra == "viz"
Requires-Dist: wandb>=0.16.0; extra == "viz"
Provides-Extra: all
Requires-Dist: unsloth_zoo; extra == "all"
Requires-Dist: bitsandbytes>=0.41.0; extra == "all"
Requires-Dist: matplotlib>=3.7.0; extra == "all"
Requires-Dist: seaborn>=0.12.0; extra == "all"
Requires-Dist: wandb>=0.16.0; extra == "all"
Requires-Dist: black>=23.0.0; extra == "all"
Requires-Dist: flake8>=6.0.0; extra == "all"
Requires-Dist: pytest>=7.0.0; extra == "all"
Requires-Dist: jupyter>=1.0.0; extra == "all"
Dynamic: author
Dynamic: home-page
Dynamic: license-file
Dynamic: requires-python
